firrtl/__init__.py
firrtl/proto/__init__.py
firrtl/proto/firrtl_pb2.py
firrtl/tests/__init__.py
firrtl/tests/test_firrtl.py
firrtl-0.1.2.dist-info/WHEEL
firrtl-0.1.2.dist-info/METADATA
firrtl-0.1.2.dist-info/RECORD
